{"cells": [{"x": 0, "y": 0, "meta": {"rendererID": "Default", "data": "&num_rows=15&num_columns=15&word0=STEROID&clue0=For a change, editors banned drug (7)&dir0=a&start_j0=0&start_k0=0&word1=DOWAGER&clue1=Carry out bet for wealthy widow (7)&dir1=a&start_j1=0&start_k1=8&word2=INSTRUMENTPANEL&clue2=Musical jury dials on dashboard (10,5)&dir2=a&start_j2=2&start_k2=0&word3=PREY&clue3=Pretty teetotaller went as target (4)&dir3=a&start_j3=4&start_k3=0&word4=DRILL&clue4=Tool used by 15 across made medico sick (5)&dir4=a&start_j4=4&start_k4=5&word5=AWAY&clue5=A method of looking distant (4)&dir5=a&start_j5=4&start_k5=11&word6=DENTIST&clue6=It tends to become canine worker (7)&dir6=a&start_j6=6&start_k6=0&word7=DRIFTED&clue7=Went with flow but dried around foot (7)&dir7=a&start_j7=6&start_k7=8&word8=OPTIMUM&clue8=Best to choose one mother (7)&dir8=a&start_j8=8&start_k8=0&word9=ORBITED&clue9=Moved around bride, to dance (7)&dir9=a&start_j9=8&start_k9=8&word10=ETNA&clue10=Volcano in Gretna Green? (4)&dir10=a&start_j10=10&start_k10=0&word11=ASSET&clue11=Valuable quality used in cassette (5)&dir11=a&start_j11=10&start_k11=5&word12=MERE&clue12=In France, mother is trifling (4)&dir12=a&start_j12=10&start_k12=11&word13=FLAGGINGSPIRITS&clue13=Attitude at half-mast when paving stones visited by ghosts (8,7)&dir13=a&start_j13=12&start_k13=0&word14=DODDERY&clue14=Shaky on legs and thirsty, holding strange final message (7)&dir14=a&start_j14=14&start_k14=0&word15=EASEDUP&clue15=Ape used disguise but relented (5,2)&dir15=a&start_j15=14&start_k15=8&word16=SHINPAD&clue16=Shield for leg and hips perhaps? (7)&dir16=d&start_j16=0&start_k16=0&word17=EASTERNSTANDARD&clue17=This time, zone oriental flag (7,8)&dir17=d&start_j17=0&start_k17=2&word18=OGRE&clue18=Some progress made by Shrek, for instance (4)&dir18=d&start_j18=0&start_k18=4&word19=DEMERIT&clue19=Looking back in entire medley, found fault (7)&dir19=d&start_j19=0&start_k19=6&word20=DANGLED&clue20=In short, Danny Glover went first and swung loosely (7)&dir20=d&start_j20=0&start_k20=8&word21=WIPE&clue21=Use tea towel with initials perfectly embroidered (4)&dir21=d&start_j21=0&start_k21=10&word22=GONEWITHTHEWIND&clue22=Mitchell classic no longer here with the flute or oboe (4,4,3,4)&dir22=d&start_j22=0&start_k22=12&word23=RELAYED&clue23=Passed on, having reclined in swampy grass (7)&dir23=d&start_j23=0&start_k23=14&word24=FIRMS&clue24=Foremost industries require manufacturing staff (5)&dir24=d&start_j24=5&start_k24=4&word25=LIMBO&clue25=State of suspension when ducking under bar (5)&dir25=d&start_j25=5&start_k25=10&word26=OVERFED&clue26=Remaining FBI agent given too much sustenance (7)&dir26=d&start_j26=8&start_k26=0&word27=MASONRY&clue27=Mary holds son in stone building (7)&dir27=d&start_j27=8&start_k27=6&word28=OVERSEE&clue28=Manage to get poetry written in Old English (7)&dir28=d&start_j28=8&start_k28=8&word29=DRESSUP&clue29=Don finery for Padre's supper segment (5,2)&dir29=d&start_j29=8&start_k29=14&word30=OGLE&clue30=Go back! The French stare amorously (4)&dir30=d&start_j30=11&start_k30=4&word31=MISS&clue31=I'm returning steamship to woman (4)&dir31=d&start_j31=11&start_k31=10&id=Cry172&title=Christines Cryptics&category=Crossword&difficulty=1&&competition=N"}}], "rows": 1, "columns": 1, "meta": {"rating": 5}}