{"cells": [{"x": 0, "y": 0, "meta": {"rendererID": "Default", "data": "&num_rows=15&num_columns=15&word0=CONCERTO&clue0=Somehow croon etc, a musical piece (8)&dir0=a&start_j0=1&start_k0=0&word1=ARABIC&clue1=Arab, I see, speaks Middle-Eastern language (6)&dir1=a&start_j1=1&start_k1=9&word2=PELE&clue2=Hoss abandons hopeless soccer legend (4)&dir2=a&start_j2=3&start_k2=0&word3=GOLDFIELDS&clue3=Gilbert and Sullivan surround old field with a source of riches (10)&dir3=a&start_j3=3&start_k3=5&word4=SILENT&clue4=Sit around Len and be quiet! (6)&dir4=a&start_j4=5&start_k4=0&word5=LADYBIRD&clue5=Little insect is spotted? (8)&dir5=a&start_j5=5&start_k5=7&word6=DEFENCE&clue6=Protection from half-made fence (7)&dir6=a&start_j6=7&start_k6=0&word7=PLACEBO&clue7=Cop able to produce sugar pill (7)&dir7=a&start_j7=7&start_k7=8&word8=PLAYPENS&clue8=Change nappy, Les, on these items of nursery furniture (8)&dir8=a&start_j8=9&start_k8=0&word9=DESIST&clue9=Des is first to stop (6)&dir9=a&start_j9=9&start_k9=9&word10=ARCHBISHOP&clue10=Posh, rich BA becomes clergyman of high status (10)&dir10=a&start_j10=11&start_k10=0&word11=CUBA&clue11=Head of state leaves scuba on Caribbean island (4)&dir11=a&start_j11=11&start_k11=11&word12=ZEBRAS&clue12=African animals half gaze on female supporters (6)&dir12=a&start_j12=13&start_k12=0&word13=LEONARDO&clue13=Leon takes wrong road to Italian master (8)&dir13=a&start_j13=13&start_k13=7&word14=HOSEPIPE&clue14=Spooner to pose hype about water conduit (8)&dir14=d&start_j14=0&start_k14=1&word15=ACRE&clue15=Area of land that is almost sacred (4)&dir15=d&start_j15=0&start_k15=3&word16=WRIGHT&clue16=Head waiter right to become aviation pioneer (6)&dir16=d&start_j16=0&start_k16=5&word17=WORLDLY&clue17=Heartless lady supports world that is sophisticated and urbane (7)&dir17=d&start_j17=0&start_k17=7&word18=DAFFODIL&clue18=Fold if ad is ruined by yellow flower (8)&dir18=d&start_j18=0&start_k18=9&word19=PAPERBACKS&clue19=Soft-covered books feature on flipside of tabloids (10)&dir19=d&start_j19=0&start_k19=11&word20=BIDDER&clue20=Bid the German be tenderer (6)&dir20=d&start_j20=0&start_k20=13&word21=EVERYWHERE&clue21=Sounds like every ware is all over the place (10)&dir21=d&start_j21=5&start_k21=3&word22=CHEWIEST&clue22=First class ewe? This is apparently the toughest to eat! (8)&dir22=d&start_j22=7&start_k22=5&word23=BUSYBODY&clue23=Hardworking group resorts to gossip (8)&dir23=d&start_j23=7&start_k23=13&word24=ASPHALT&clue24=Snake! Stop! It's bitumen! (7)&dir24=d&start_j24=8&start_k24=7&word25=LURKED&clue25=Laid in wait and lured first kangaroo inside (6)&dir25=d&start_j25=9&start_k25=1&word26=DEPLOY&clue26=Strategically set up ploy to replace pot in depot (6)&dir26=d&start_j26=9&start_k26=9&word27=CLAY&clue27=Oddly, Calgary produces mud for potters (4)&dir27=d&start_j27=11&start_k27=11&id=Ncry241&title=Brian Cryptic&category=Crossword&difficulty=1&&competition=N"}}], "rows": 1, "columns": 1, "meta": {"rating": 5}}