{"cells": [{"x": 0, "y": 0, "meta": {"rendererID": "Default", "data": "&num_rows=15&num_columns=15&word0=BULLDOZED&clue0=Bovine creature had a nap, having been flattened! (9)&dir0=a&start_j0=0&start_k0=0&word1=WHEEL&clue1=Revolutionary invention, we'll say (5)&dir1=a&start_j1=0&start_k1=10&word2=ATTIC&clue2=Lattice held in loft (5)&dir2=a&start_j2=2&start_k2=0&word3=USEDCAR&clue3=Crusade to renovate second-hand vehicle (4,3)&dir3=a&start_j3=2&start_k3=8&word4=TIE&clue4=Dead heat? What a bind! (3)&dir4=a&start_j4=4&start_k4=0&word5=IDIOTS&clue5=Initially dolts, ignoramuses or thoughtless simpletons (6)&dir5=a&start_j5=4&start_k5=4&word6=BLUE&clue6=Argument with a redhead? (4)&dir6=a&start_j6=4&start_k6=11&word7=DEBUNKS&clue7=Shows to be false and removes from bed (7)&dir7=a&start_j7=6&start_k7=0&word8=DAVINCI&clue8=Vic and I converted Leonardo, a painter (2,5)&dir8=a&start_j8=6&start_k8=8&word9=FOXTROT&clue9=Dance makes vixen jog (7)&dir9=a&start_j9=8&start_k9=0&word10=AIRPORT&clue10=Rescheduled a trip, or flight terminus (7)&dir10=a&start_j10=8&start_k10=8&word11=URGE&clue11=Encourage surgeon to drop off son (4)&dir11=a&start_j11=10&start_k11=0&word12=CORTEX&clue12=Caught ex discussing the outer layer of brain (6)&dir12=a&start_j12=10&start_k12=5&word13=EGO&clue13=At heart, Gregory shows conceit (3)&dir13=a&start_j13=10&start_k13=12&word14=INSULIN&clue14=In Sioux, Lyn heard what diabetics need (7)&dir14=a&start_j14=12&start_k14=0&word15=ECLAT&clue15=Great success involving a Celt (5)&dir15=a&start_j15=12&start_k15=10&word16=GLOOM&clue16=Groom went from right to left in darkness (5)&dir16=a&start_j16=14&start_k16=0&word17=EXPEDIENT&clue17=Profitable to extend pie redistribution (9)&dir17=a&start_j17=14&start_k17=6&word18=BEAST&clue18=Best when surrounding a wild animal (5)&dir18=d&start_j18=0&start_k18=0&word19=LETTERBOX&clue19=Postal receptacle has better locks, according to Spooner (9)&dir19=d&start_j19=0&start_k19=2&word20=DICTIONARY&clue20=Book used by crossworders became diary to Nic (10)&dir20=d&start_j20=0&start_k20=4&word21=ZOMBIES&clue21=Mob size has changed - now they're walking corpses! (7)&dir21=d&start_j21=0&start_k21=6&word22=DAUNTED&clue22=Overwhelmed old Aunt Edith somewhat (7)&dir22=d&start_j22=0&start_k22=8&word23=WREN&clue23=Lawrence held tiny warbler (4)&dir23=d&start_j23=0&start_k23=10&word24=EXCEL&clue24=Roman said 10.50 is the time to do well (5)&dir24=d&start_j24=0&start_k24=12&word25=LARCENIST&clue25=Burglar wreaked havoc with clarinets (9)&dir25=d&start_j25=0&start_k25=14&word26=OVEREXTEND&clue26=Inside alcove, Rex tends to take on too much (10)&dir26=d&start_j26=5&start_k26=10&word27=DIFFUSING&clue27=Spreading out in Cardiff, using parts (9)&dir27=d&start_j27=6&start_k27=0&word28=NOONEELSE&clue28=In the afternoon, eels enclosed, but not another person (2-3,4)&dir28=d&start_j28=6&start_k28=12&word29=TROUNCE&clue29=At heart, Castro uncertain of defeat (7)&dir29=d&start_j29=8&start_k29=6&word30=ANTWERP&clue30=Reconstructed new part of port in Belgium (7)&dir30=d&start_j30=8&start_k30=8&word31=GUSTO&clue31=Zest for life in August only (5)&dir31=d&start_j31=10&start_k31=2&word32=OCTET&clue32=Concoct ethics involving eight singers (5)&dir32=d&start_j32=10&start_k32=14&word33=CLAM&clue33=Malcolm went back partly for shellfish (4)&dir33=d&start_j33=11&start_k33=4&id=Incry002&title=Internet Cryptic&category=Crossword&difficulty=1&&competition=N"}}], "rows": 1, "columns": 1, "meta": {"rating": 5}}