{"cells": [{"x": 0, "y": 0, "meta": {"rendererID": "Default", "data": "&num_rows=15&num_columns=15&word0=ENDOWED&clue0=After finale, was obliged to pay for being gifted (7)&dir0=a&start_j0=0&start_k0=0&word1=COURAGE&clue1=Bravery could start at our age (7)&dir1=a&start_j1=0&start_k1=8&word2=ELY&clue2=Eel, I say, comes from Fens city (3)&dir2=a&start_j2=2&start_k2=0&word3=TIMBER&clue3=Cutting remark made by lumberjack (6)&dir3=a&start_j3=2&start_k3=4&word4=CAME&clue4=Turned up when auction item left Camelot (4)&dir4=a&start_j4=2&start_k4=11&word5=APPROXIMATELY&clue5=Nearly eleven, mate, extremely likely to be on appro (13)&dir5=a&start_j5=4&start_k5=0&word6=DEADEASY&clue6=A sad-eyed transformation is quite simple (4,4)&dir6=a&start_j6=6&start_k6=0&word7=DOZEN&clue7=Practise form of Buddhism one and two (5)&dir7=a&start_j7=6&start_k7=9&word8=DREAD&clue8=Greatly fear disturbing adder (5)&dir8=a&start_j8=8&start_k8=1&word9=SMUDGING&clue9=Smearing this mud gingerly inside (8)&dir9=a&start_j9=8&start_k9=7&word10=SOMNAMBULISTS&clue10=Wanderers of the Dreamtime (13)&dir10=a&start_j10=10&start_k10=2&word11=OVAL&clue11=Eggs left on field (4)&dir11=a&start_j11=12&start_k11=0&word12=GALLEY&clue12=Sailors' kitchen has no right to be a gallery! (6)&dir12=a&start_j12=12&start_k12=5&word13=APE&clue13=Chaperon held monkey (3)&dir13=a&start_j13=12&start_k13=12&word14=TREMBLE&clue14=Shake extremities of treacherous bramble (7)&dir14=a&start_j14=14&start_k14=0&word15=SURREAL&clue15=Terrible RSA rule flies in face of reality (7)&dir15=a&start_j15=14&start_k15=8&word16=EMERALDS&clue16=Dream Les spoilt gems (8)&dir16=d&start_j16=0&start_k16=0&word17=DRYUP&clue17=Run out and use a tea towel (3,2)&dir17=d&start_j17=0&start_k17=2&word18=WITHOPENARMS&clue18=How unstitched sleeves might be welcomed? (4,4,4)&dir18=d&start_j18=0&start_k18=4&word19=DUMMIES&clue19=Pacifiers that stand in shop windows (7)&dir19=d&start_j19=0&start_k19=6&word20=CAESAR&clue20=Hears and sees a Roman leader (6)&dir20=d&start_j20=0&start_k20=8&word21=ANALYSE&clue21=Break down when Anna lies out loud (7)&dir21=d&start_j21=0&start_k21=12&word22=EVERTS&clue22=Reverts to being headless and turns inside out (6)&dir22=d&start_j22=0&start_k22=14&word23=RECORDPLAYER&clue23=Register sports competitor on dated sound system (6,6)&dir23=d&start_j23=3&start_k23=10&word24=EGGSHELL&clue24=Sort of porcelain that keeps a chick safe (8)&dir24=d&start_j24=7&start_k24=14&word25=RESTATE&clue25=Repeat what the remainder consumed (7)&dir25=d&start_j25=8&start_k25=2&word26=MOBILES&clue26=Phones that hang in the nursery (7)&dir26=d&start_j26=8&start_k26=8&word27=IMPORT&clue27=I'm left on boat with overseas product (6)&dir27=d&start_j27=9&start_k27=0&word28=HARARE&clue28=Mocking laugh unusual in Zimbabwe (6)&dir28=d&start_j28=9&start_k28=6&word29=SHAPE&clue29=Form a new phase (5)&dir29=d&start_j29=10&start_k29=12&id=OLCryptic069&title=Online Cryptics&category=Crossword&difficulty=1&&competition=N"}}], "rows": 1, "columns": 1, "meta": {"rating": 5}}