{"cells": [{"x": 0, "y": 0, "meta": {"rendererID": "Default", "data": "&num_rows=15&num_columns=15&word0=SUNLAMP&clue0=Slam pun about artificial tanning device (3,4)&dir0=a&start_j0=0&start_k0=0&word1=CAPABLE&clue1=Competent at wrapping Pa in cable&dir1=a&start_j1=0&start_k1=8&word2=ENTRANT&clue2=Reg leaves Regent to rant at competitor&dir2=a&start_j2=2&start_k2=0&word3=SHEARED&clue3=Are in shed to be clipped&dir3=a&start_j3=2&start_k3=8&word4=BRIMSTONE&clue4=Sulphur trims bone somewhat&dir4=a&start_j4=4&start_k4=0&word5=DRIER&clue5=Rider out to get less wet&dir5=a&start_j5=4&start_k5=10&word6=THROB&clue6=Starts as the hearty rhythm of blood&dir6=a&start_j6=6&start_k6=0&word7=ROBINHOOD&clue7=Sherwood Forest outlaw's name is Horobod? (5,4)&dir7=a&start_j7=6&start_k7=6&word8=JELLYFISH&clue8=Sea creature made from half jellybeans, half starfish&dir8=a&start_j8=8&start_k8=0&word9=MUSIC&clue9=Endlessly muse, I see, about songs&dir9=a&start_j9=8&start_k9=10&word10=PANIC&clue10=Plain zinc oddly creates terror&dir10=a&start_j10=10&start_k10=0&word11=COMMUNISM&clue11=Mmm, cousin crazy about classless society&dir11=a&start_j11=10&start_k11=6&word12=TRIBUNE&clue12=Brute in transformation into ancient Roman official&dir12=a&start_j12=12&start_k12=0&word13=ALBANIA&clue13=Final ban I announce includes Eastern European country&dir13=a&start_j13=12&start_k13=8&word14=RESISTS&clue14=Opposes stress I stir up&dir14=a&start_j14=14&start_k14=0&word15=SERPENT&clue15=Snake is spent swallowing Queen&dir15=a&start_j15=14&start_k15=8&word16=SHERBET&clue16=Mixes up her best fruity powder&dir16=d&start_j16=0&start_k16=0&word17=NATTIER&clue17=Raised tan on tier to look more dapper&dir17=d&start_j17=0&start_k17=2&word18=AMASS&clue18=Stockpile in a Catholic church service&dir18=d&start_j18=0&start_k18=4&word19=POTPOURRI&clue19=Take middle of teapot, pour, rinse and find dried flower mixture&dir19=d&start_j19=0&start_k19=6&word20=CASTE&clue20=Case for including top types in Indian social order&dir20=d&start_j20=0&start_k20=8&word21=PSEUDONYM&clue21=Spud money used to create fictitious name&dir21=d&start_j21=0&start_k21=10&word22=BURRITO&clue22=Burro eats it, this Spanish dish&dir22=d&start_j22=0&start_k22=12&word23=ENDURED&clue23=Tolerated putting end to terribly rude characters&dir23=d&start_j23=0&start_k23=14&word24=BOYSCOUTS&clue24=Those who are always prepared buy cots so damaged (3,6)&dir24=d&start_j24=6&start_k24=4&word25=BOHEMIANS&clue25=Bo hems Ian inside with unconventional types&dir25=d&start_j25=6&start_k25=8&word26=JUPITER&clue26=Asked, \"D'you pit her against king of the gods?\"&dir26=d&start_j26=8&start_k26=0&word27=LENTILS&clue27=Lent half of Basil's legumes&dir27=d&start_j27=8&start_k27=2&word28=SCIENCE&clue28=Even psychic Ed nicked has knowledge of the world&dir28=d&start_j28=8&start_k28=12&word29=COMPACT&clue29=Compress cosmetic case&dir29=d&start_j29=8&start_k29=14&word30=CHESS&clue30=One hundred Romans take on Hess at game of strategy&dir30=d&start_j30=10&start_k30=6&word31=UMBER&clue31=Cut down lumber for brown pigment&dir31=d&start_j31=10&start_k31=10&id=Ncry196&title=Brian Cryptic&category=Crossword&difficulty=1&&competition=N"}}], "rows": 1, "columns": 1, "meta": {"rating": 5}}